Metadata-Version: 1.2
Name: mini-redis
Version: 0.1.1
Summary: A lib to store structured data in redis using less memory
Home-page: http://github.com/polvoazul/mini-redis
Author: Fred Israel
Author-email: UNKNOWN
License: unlicense
Platform: UNKNOWN
Requires-Python: >=3.3, <4
